lestpy/__init__.py
lestpy/lbm_model.py
lestpy/outlier.py
lestpy/visualize.py
lestpy-0.0.11.dist-info/METADATA
lestpy-0.0.11.dist-info/WHEEL
lestpy-0.0.11.dist-info/top_level.txt
lestpy-0.0.11.dist-info/RECORD
