Metadata-Version: 2.1
Name: lestpy
Version: 0.0.11
Summary: Regression model with logical interactions
Home-page: https://github.com/Pyonysos/lestpy
Author: Pyonysos (Paul-Hubert Baudelet)
Author-email: 
License: UNKNOWN
Keywords: python,modeling,regression
Platform: UNKNOWN
Classifier: Development Status :: 2 - Pre-Alpha
Classifier: Intended Audience :: Science/Research
Classifier: Programming Language :: Python :: 3
Classifier: License :: OSI Approved :: GNU General Public License v3 or later (GPLv3+)
Classifier: Operating System :: Unix
Classifier: Operating System :: Microsoft :: Windows
Requires-Dist: pandas
Requires-Dist: matplotlib
Requires-Dist: statsmodels
Requires-Dist: SALib
